opinf/__init__.py
opinf/errors.py
opinf/basis/__init__.py
opinf/basis/_base.py
opinf/basis/_linear.py
opinf/basis/_multi.py
opinf/basis/_pod.py
opinf/ddt/__init__.py
opinf/ddt/_base.py
opinf/ddt/_finite_difference.py
opinf/ddt/_interpolation.py
opinf/lift/__init__.py
opinf/lift/_base.py
opinf/lift/_polynomial.py
opinf/lstsq/__init__.py
opinf/lstsq/_base.py
opinf/lstsq/_tikhonov.py
opinf/lstsq/_total.py
opinf/lstsq/_tsvd.py
opinf/models/__init__.py
opinf/models/_utils.py
opinf/models/mono/__init__.py
opinf/models/mono/_base.py
opinf/models/mono/_nonparametric.py
opinf/models/mono/_parametric.py
opinf/models/multi/__init__.py
opinf/models/multi/_base.py
opinf/models/multi/_nonparametric.py
opinf/models/multi/_parametric.py
opinf/operators/__init__.py
opinf/operators/_affine.py
opinf/operators/_base.py
opinf/operators/_interpolate.py
opinf/operators/_nonparametric.py
opinf/operators/_polynomial_operator.py
opinf/operators/_utils.py
opinf/post/__init__.py
opinf/post/_errors.py
opinf/pre/__init__.py
opinf/pre/_base.py
opinf/pre/_multi.py
opinf/pre/_shiftscale.py
opinf/roms/__init__.py
opinf/roms/_base.py
opinf/roms/_bayes.py
opinf/roms/_nonparametric.py
opinf/roms/_parametric.py
opinf/utils/__init__.py
opinf/utils/_gridsearch.py
opinf/utils/_hdf5.py
opinf/utils/_mpl_config.py
opinf/utils/_repr.py
opinf/utils/_reprojection.py
opinf/utils/_requires.py
opinf/utils/_timer.py
opinf-0.6.0.dist-info/licenses/LICENSE
opinf-0.6.0.dist-info/METADATA
opinf-0.6.0.dist-info/WHEEL
opinf-0.6.0.dist-info/top_level.txt
opinf-0.6.0.dist-info/RECORD
