Metadata-Version: 2.4
Name: opinf
Version: 0.6.0
Summary: Operator Inference for data-driven model reduction of dynamical systems.
Author-email: "Shane A. McQuarrie, Karen E. Willcox, and OpInf Contributors" <shanemcq@mathematics.byu.edu>
Maintainer-email: "Shane A. McQuarrie" <shanemcq@mathematics.byu.edu>
License: MIT License
Project-URL: homepage, https://operator-inference.github.io/opinf/source/index.html
Project-URL: documentation, https://operator-inference.github.io/opinf/source/index.html
Project-URL: repository, https://github.com/operator-inference/opinf.git
Keywords: operator inference,model reduction,data-driven model reduction,scientific machine learning
Classifier: Programming Language :: Python :: 3
Classifier: Natural Language :: English
Classifier: License :: OSI Approved :: MIT License
Classifier: Operating System :: OS Independent
Classifier: Topic :: Scientific/Engineering
Classifier: Intended Audience :: Science/Research
Classifier: Development Status :: 4 - Beta
Requires-Python: >=3.10
License-File: LICENSE
Requires-Dist: h5py>=3.9.0
Requires-Dist: numpy>=1.23.2
Requires-Dist: scipy>=1.10.1
Requires-Dist: matplotlib>=3.7
Requires-Dist: scikit-learn>=1.3.0
Provides-Extra: dev
Requires-Dist: bibtexparser>=2.0.0b7; extra == "dev"
Requires-Dist: black==24.4.2; extra == "dev"
Requires-Dist: flake8==7.0.0; extra == "dev"
Requires-Dist: jupyterlab; extra == "dev"
Requires-Dist: notebook; extra == "dev"
Requires-Dist: pandas; extra == "dev"
Requires-Dist: pre-commit>=3.7.1; extra == "dev"
Requires-Dist: pytest; extra == "dev"
Requires-Dist: pytest-cov; extra == "dev"
Requires-Dist: tox>=4; extra == "dev"
Dynamic: license-file
